conciergelib/__init__.py
conciergelib-0.0.1.dist-info/METADATA
conciergelib-0.0.1.dist-info/WHEEL
conciergelib-0.0.1.dist-info/top_level.txt
conciergelib-0.0.1.dist-info/RECORD
