Metadata-Version: 2.1
Name: conciergelib
Version: 0.0.1
Summary: conciergelib package lock
